cowsay.py
py.typed
cowsay_python-1.0.2.dist-info/METADATA
cowsay_python-1.0.2.dist-info/WHEEL
cowsay_python-1.0.2.dist-info/licenses/LICENSE
cowsay_python-1.0.2.dist-info/RECORD
