Metadata-Version: 2.3
Name: cowsay-python
Version: 1.0.2
Summary: Very basic cowsay implementation
Project-URL: homepage, https://github.com/carderne/cowsay-python
Project-URL: repository, https://github.com/carderne/cowsay-python
Author-email: Chris Arderne <chris@rdrn.me>
License: MIT License
License-File: LICENSE
Keywords: cowsay
Classifier: Environment :: Console
Classifier: Intended Audience :: Developers
Classifier: License :: OSI Approved :: MIT License
Classifier: Operating System :: Unix
Classifier: Programming Language :: Python
Classifier: Programming Language :: Python :: 3.9
Classifier: Programming Language :: Python :: 3.10
Classifier: Programming Language :: Python :: 3.11
Classifier: Programming Language :: Python :: 3.12
Requires-Python: >=3.9
